pyrose2-2.0.1.dist-info/licenses/LICENSE.txt
rose2/__init__.py
rose2/cli.py
rose2/rose_bamToGFF.py
rose2/rose_geneMapper.py
rose2/rose_main.py
rose2/utils.py
rose2/R/ROSE_callSuper.R
rose2/annotation/hg18_refseq.ucsc
rose2/annotation/hg19_refseq.ucsc
rose2/annotation/hg38_refseq.ucsc
rose2/annotation/mm10_refseq.ucsc
rose2/annotation/mm8_refseq.ucsc
rose2/annotation/mm9_refseq.ucsc
pyrose2-2.0.1.dist-info/METADATA
pyrose2-2.0.1.dist-info/WHEEL
pyrose2-2.0.1.dist-info/entry_points.txt
pyrose2-2.0.1.dist-info/top_level.txt
pyrose2-2.0.1.dist-info/RECORD
