Metadata-Version: 2.4
Name: pyrose2
Version: 2.0.1
Summary: Rank Ordering of Super-Enhancers - A tool for identifying super-enhancers from ChIP-seq data
Author: St. Jude Children's Research Hospital (Python 3 Port)
Author-email: "Richard Young Lab (Original)" <youngcomputation@wi.mit.edu>, "Ming Tang (Modernization & PyPI)" <tangming2005@gmail.com>
Maintainer-email: Ming Tang <tangming2005@gmail.com>
License: Apache-2.0
Project-URL: Homepage, https://github.com/crazyhottommy/ROSE2
Project-URL: Documentation, https://github.com/crazyhottommy/ROSE2/blob/master/README.md
Project-URL: Repository, https://github.com/crazyhottommy/ROSE2
Project-URL: Bug Tracker, https://github.com/crazyhottommy/ROSE2/issues
Keywords: bioinformatics,genomics,chip-seq,super-enhancers,enhancers,epigenetics
Classifier: Development Status :: 5 - Production/Stable
Classifier: Intended Audience :: Science/Research
Classifier: License :: OSI Approved :: Apache Software License
Classifier: Operating System :: OS Independent
Classifier: Programming Language :: Python :: 3
Classifier: Programming Language :: Python :: 3.8
Classifier: Programming Language :: Python :: 3.9
Classifier: Programming Language :: Python :: 3.10
Classifier: Programming Language :: Python :: 3.11
Classifier: Programming Language :: Python :: 3.12
Classifier: Topic :: Scientific/Engineering :: Bio-Informatics
Requires-Python: >=3.8
License-File: LICENSE.txt
Requires-Dist: numpy>=1.20.0
Provides-Extra: dev
Requires-Dist: pytest>=7.0; extra == "dev"
Requires-Dist: pytest-cov>=4.0; extra == "dev"
Requires-Dist: black>=23.0; extra == "dev"
Requires-Dist: flake8>=6.0; extra == "dev"
Requires-Dist: mypy>=1.0; extra == "dev"
Dynamic: license-file
